LICENSE
MANIFEST.in
README.md
setup.py
libsgfdata/__init__.py
libsgfdata/cmd.py
libsgfdata/cmd_depth.py
libsgfdata/cmd_depth_to_material.py
libsgfdata/cmd_dtm.py
libsgfdata/cmd_normalize.py
libsgfdata/comments.csv
libsgfdata/data-flags.csv
libsgfdata/data.csv
libsgfdata/dtm.py
libsgfdata/dumper.py
libsgfdata/main.csv
libsgfdata/metadata.py
libsgfdata/method.csv
libsgfdata/methods.csv
libsgfdata/normalizer.py
libsgfdata/parser.py
libsgfdata/validate.py
libsgfdata.egg-info/PKG-INFO
libsgfdata.egg-info/SOURCES.txt
libsgfdata.egg-info/dependency_links.txt
libsgfdata.egg-info/entry_points.txt
libsgfdata.egg-info/requires.txt
libsgfdata.egg-info/top_level.txt