Metadata-Version: 2.1
Name: libsgfdata
Version: 0.0.23
Summary: Parser for Swedish Geotechnical Society data format
Home-page: https://github.com/emerald-geomodelling/libsgfdata
Author: Egil Moeller
Author-email: em@emrld.no
License: UNKNOWN
Platform: UNKNOWN
Provides-Extra: cmd
Provides-Extra: dtm
License-File: LICENSE
